gptcomet-2.4.1.dist-info/METADATA
gptcomet-2.4.1.dist-info/WHEEL
gptcomet-2.4.1.dist-info/entry_points.txt
gptcomet-2.4.1.dist-info/licenses/LICENSE
gptcomet/__init__.py
gptcomet/bin/gptcomet_amd64_linux
gptcomet-2.4.1.dist-info/RECORD
