Metadata-Version: 2.1
Name: gptcomet
Version: 2.4.1
Summary: GPTComet: AI-Powered Git Commit Message Generator.
Keywords: ai,git,commit,message,ai-powered,commit-message,gptcomet,chatgpt
Author-Email: belingud <im.victor@qq.com>
License: MIT license
Classifier: Development Status :: 3 - Alpha
Classifier: Intended Audience :: Developers
Classifier: License :: OSI Approved :: MIT License
Classifier: Operating System :: OS Independent
Classifier: Programming Language :: Python
Classifier: Programming Language :: Python :: 3
Classifier: Programming Language :: Python :: 3.8
Classifier: Programming Language :: Python :: 3.9
Classifier: Programming Language :: Python :: 3.10
Classifier: Programming Language :: Python :: 3.11
Classifier: Programming Language :: Python :: 3.12
Classifier: Programming Language :: Python :: 3.13
Classifier: Topic :: Software Development :: Code Generators
Classifier: Topic :: Software Development :: Libraries :: Python Modules
Project-URL: Homepage, https://github.com/belingud/gptcomet
Project-URL: Repository, https://github.com/belingud/gptcomet
Project-URL: Documentation, https://github.com/belingud/gptcomet
Requires-Python: <4.0,>=3.9
